greenletio/__init__.py
greenletio/cli.py
greenletio/core.py
greenletio/io.py
greenletio/patcher.py
greenletio/green/__init__.py
greenletio/green/select.py
greenletio/green/selectors.py
greenletio/green/socket.py
greenletio/green/ssl.py
greenletio/green/threading.py
greenletio/green/time.py
greenletio-0.11.0.dist-info/LICENSE
greenletio-0.11.0.dist-info/METADATA
greenletio-0.11.0.dist-info/WHEEL
greenletio-0.11.0.dist-info/entry_points.txt
greenletio-0.11.0.dist-info/top_level.txt
greenletio-0.11.0.dist-info/RECORD
