Metadata-Version: 2.1
Name: greenletio
Version: 0.11.0
Summary: Asyncio integration with sync code using greenlets.
Author-email: Miguel Grinberg <miguel.grinberg@gmail.com>
Project-URL: Homepage, https://github.com/miguelgrinberg/greenletio
Project-URL: Bug Tracker, https://github.com/miguelgrinberg/greenletio/issues
Classifier: Intended Audience :: Developers
Classifier: Programming Language :: Python :: 3
Classifier: License :: OSI Approved :: MIT License
Classifier: Operating System :: OS Independent
Requires-Python: >=3.7
License-File: LICENSE
Requires-Dist: greenlet
Provides-Extra: docs
Requires-Dist: sphinx; extra == "docs"
